Workbook

Sheet Sheet1
A1: word | B1: frequency | C1: tag
A2: 毛克力 | B2: 326 | C2: characters known
A3: 就像 | B3: 216 | C3: characters known
A4: 点赞 | B4: 138 | C4: partial characters known
A5: 更多 | B5: 118 | C5: characters known
A6: 不可能 | B6: 113 | C6: characters known
A7: 珍珠 | B7: 108 | C7: No tags
A8: 没人 | B8: 106 | C8: characters known
A9: 执行 | B9: 95 | C9: characters known
A10: 替 | B10: 79 | C10: No tags
A11: 巴鲁 | B11: 75 | C11: characters known
A12: 做好 | B12: 70 | C12: characters known
A13: 极了 | B13: 66 | C13: characters known
... A1118: 龟兵 | B1118: 0 | C1118: No tags

Sheet Sheet2
A1: Word | B1: Found
A2: 埃 | B2: =VLOOKUP(A2,Sheet4!$A$1:$A$1593,1,0) -> #N/A
A3: 拔 | B3: =VLOOKUP(A3,Sheet4!$A$1:$A$1593,1,0) -> 拔
A4: 饱 | B4: =VLOOKUP(A4,Sheet4!$A$1:$A$1593,1,0) -> #N/A
A5: 崩 | B5: =VLOOKUP(A5,Sheet4!$A$1:$A$1593,1,0) -> #N/A
A6: 笔 | B6: =VLOOKUP(A6,Sheet4!$A$1:$A$1593,1,0) -> #N/A
A7: 玻 | B7: =VLOOKUP(A7,Sheet4!$A$1:$A$1593,1,0) -> #N/A
A8: 补 | B8: =VLOOKUP(A8,Sheet4!$A$1:$A$1593,1,0) -> #N/A
A9: 炒 | B9: =VLOOKUP(A9,Sheet4!$A$1:$A$1593,1,0) -> #N/A
A10: 尺 | B10: =VLOOKUP(A10,Sheet4!$A$1:$A$1593,1,0) -> #N/A
A11: 粗 | B11: =VLOOKUP(A11,Sheet4!$A$1:$A$1593,1,0) -> #N/A
A12: 戴 | B12: =VLOOKUP(A12,Sheet4!$A$1:$A$1593,1,0) -> #N/A
A13: 担 | B13: =VLOOKUP(A13,Sheet4!$A$1:$A$1593,1,0) -> 担
... A360: 顶 | B360: =VLOOKUP(A360,Sheet4!$A$1:$A$1593,1,0) -> 顶

Sheet Sheet4
A1: 势
A2: 纹
A3: 弊
A4: 眠
A5: 毒
A6: 钩
A7: 顾
A8: 省
A9: 劝
A10: 免
A11: 艾
A12: 荣
... A1593: 石

Sheet Sheet3
A1: Word | B1: Length
A2: 势 | B2: =LEN(A2) -> 1
A3: 组织 | B3: =LEN(A3) -> 2
A4: 不得不 | B4: =LEN(A4) -> 3
A5: 纹 | B5: =LEN(A5) -> 1
A6: 民众 | B6: =LEN(A6) -> 2
A7: 降世神通 | B7: =LEN(A7) -> 4
A8: 桃子 | B8: =LEN(A8) -> 2
A9: 部长 | B9: =LEN(A9) -> 2
A10: 弊 | B10: =LEN(A10) -> 1
A11: 排队 | B11: =LEN(A11) -> 2
A12: 眠 | B12: =LEN(A12) -> 1
A13: 军团 | B13: =LEN(A13) -> 2
... A4412: 石 | B4412: =LEN(A4412) -> 1
