Workbook

Sheet Sheet1
A1: Current known in LingQ | B1: In Skritter? | C1: Move to ignored?
A2: 度 | B2: =VLOOKUP(A2,'Skritter words'!$A$1:$A$4411,1,0) -> 度
A3: 友好 | B3: =VLOOKUP(A3,'Skritter words'!$A$1:$A$4411,1,0) -> 友好
A4: 人头 | B4: =VLOOKUP(A4,'Skritter words'!$A$1:$A$4411,1,0) -> 人头
A5: 就 | B5: =VLOOKUP(A5,'Skritter words'!$A$1:$A$4411,1,0) -> 就
A6: 应该 | B6: =VLOOKUP(A6,'Skritter words'!$A$1:$A$4411,1,0) -> 应该
A7: 怎么样 | B7: =VLOOKUP(A7,'Skritter words'!$A$1:$A$4411,1,0) -> 怎么样
A8: 等等等等 | B8: =VLOOKUP(A8,'Skritter words'!$A$1:$A$4411,1,0) -> #N/A | C8: x
A9: 只是 | B9: =VLOOKUP(A9,'Skritter words'!$A$1:$A$4411,1,0) -> 只是
A10: 见过 | B10: =VLOOKUP(A10,'Skritter words'!$A$1:$A$4411,1,0) -> #N/A | C10: x
A11: 帮助 | B11: =VLOOKUP(A11,'Skritter words'!$A$1:$A$4411,1,0) -> 帮助
A12: 这么 | B12: =VLOOKUP(A12,'Skritter words'!$A$1:$A$4411,1,0) -> 这么
A13: 说 | B13: =VLOOKUP(A13,'Skritter words'!$A$1:$A$4411,1,0) -> 说
A14: 她 | B14: =VLOOKUP(A14,'Skritter words'!$A$1:$A$4411,1,0) -> 她
A15: 丿 | B15: =VLOOKUP(A15,'Skritter words'!$A$1:$A$4411,1,0) -> 丿
A16: 为止 | B16: =VLOOKUP(A16,'Skritter words'!$A$1:$A$4411,1,0) -> 为止
A17: 乃 | B17: =VLOOKUP(A17,'Skritter words'!$A$1:$A$4411,1,0) -> 乃
A18: 之后 | B18: =VLOOKUP(A18,'Skritter words'!$A$1:$A$4411,1,0) -> 之后
A19: 乍 | B19: =VLOOKUP(A19,'Skritter words'!$A$1:$A$4411,1,0) -> 乍
A20: 乙 | B20: =VLOOKUP(A20,'Skritter words'!$A$1:$A$4411,1,0) -> 乙
A21: 九 | B21: =VLOOKUP(A21,'Skritter words'!$A$1:$A$4411,1,0) -> 九
A22: 九点九点 | B22: =VLOOKUP(A22,'Skritter words'!$A$1:$A$4411,1,0) -> #N/A | C22: x
A23: 习 | B23: =VLOOKUP(A23,'Skritter words'!$A$1:$A$4411,1,0) -> 习
A24: 书 | B24: =VLOOKUP(A24,'Skritter words'!$A$1:$A$4411,1,0) -> 书
A25: 亅 | B25: =VLOOKUP(A25,'Skritter words'!$A$1:$A$4411,1,0) -> 亅
A26: 二十 | B26: =VLOOKUP(A26,'Skritter words'!$A$1:$A$4411,1,0) -> 二十
A27: 奶奶 | B27: =VLOOKUP(A27,'Skritter words'!$A$1:$A$4411,1,0) -> 奶奶
A28: 女王 | B28: =VLOOKUP(A28,'Skritter words'!$A$1:$A$4411,1,0) -> 女王
A29: 尢 | B29: =VLOOKUP(A29,'Skritter words'!$A$1:$A$4411,1,0) -> 尢
A30: 好像 | B30: =VLOOKUP(A30,'Skritter words'!$A$1:$A$4411,1,0) -> 好像
A31: 尤 | B31: =VLOOKUP(A31,'Skritter words'!$A$1:$A$4411,1,0) -> 尤
A32: 尸 | B32: =VLOOKUP(A32,'Skritter words'!$A$1:$A$4411,1,0) -> 尸
A33: 尼 | B33: =VLOOKUP(A33,'Skritter words'!$A$1:$A$4411,1,0) -> 尼
A34: 尼克 | B34: =VLOOKUP(A34,'Skritter words'!$A$1:$A$4411,1,0) -> 尼克
A35: 奶 | B35: =VLOOKUP(A35,'Skritter words'!$A$1:$A$4411,1,0) -> 奶
A36: 好不 | B36: =VLOOKUP(A36,'Skritter words'!$A$1:$A$4411,1,0) -> #N/A | C36: x
A37: 好不好 | B37: =VLOOKUP(A37,'Skritter words'!$A$1:$A$4411,1,0) -> 好不好
A38: 好人 | B38: =VLOOKUP(A38,'Skritter words'!$A$1:$A$4411,1,0) -> 好人
A39: 好吃 | B39: =VLOOKUP(A39,'Skritter words'!$A$1:$A$4411,1,0) -> 好吃
A40: 好吃不好吃 | B40: =VLOOKUP(A40,'Skritter words'!$A$1:$A$4411,1,0) -> 好吃不好吃
A41: 好吗 | B41: =VLOOKUP(A41,'Skritter words'!$A$1:$A$4411,1,0) -> 好吗
A42: 好吧 | B42: =VLOOKUP(A42,'Skritter words'!$A$1:$A$4411,1,0) -> 好吧
A43: 好喝 | B43: =VLOOKUP(A43,'Skritter words'!$A$1:$A$4411,1,0) -> 好喝
A44: 好的 | B44: =VLOOKUP(A44,'Skritter words'!$A$1:$A$4411,1,0) -> 好的
A45: 呃 | B45: =VLOOKUP(A45,'Skritter words'!$A$1:$A$4411,1,0) -> 呃
A46: 吗 | B46: =VLOOKUP(A46,'Skritter words'!$A$1:$A$4411,1,0) -> 吗
A47: 同学 | B47: =VLOOKUP(A47,'Skritter words'!$A$1:$A$4411,1,0) -> 同学
A48: 名 | B48: =VLOOKUP(A48,'Skritter words'!$A$1:$A$4411,1,0) -> 名
... A56: 十一 | B56: =VLOOKUP(A56,'Skritter words'!$A$1:$A$4411,1,0) -> 十一
A57: 十五 | B57: =VLOOKUP(A57,'Skritter words'!$A$1:$A$4411,1,0) -> #N/A | C57: x
A58: 发 | B58: =VLOOKUP(A58,'Skritter words'!$A$1:$A$4411,1,0) -> 发
A59: 千 | B59: =VLOOKUP(A59,'Skritter words'!$A$1:$A$4411,1,0) -> 千
A60: 午 | B60: =VLOOKUP(A60,'Skritter words'!$A$1:$A$4411,1,0) -> 午
A61: 午饭 | B61: =VLOOKUP(A61,'Skritter words'!$A$1:$A$4411,1,0) -> 午饭
A62: 半 | B62: =VLOOKUP(A62,'Skritter words'!$A$1:$A$4411,1,0) -> 半
A63: 卜 | B63: =VLOOKUP(A63,'Skritter words'!$A$1:$A$4411,1,0) -> 卜
A64: 卩 | B64: =VLOOKUP(A64,'Skritter words'!$A$1:$A$4411,1,0) -> 卩
A65: 厂 | B65: =VLOOKUP(A65,'Skritter words'!$A$1:$A$4411,1,0) -> 厂
A66: 原 | B66: =VLOOKUP(A66,'Skritter words'!$A$1:$A$4411,1,0) -> 原
A67: 占 | B67: =VLOOKUP(A67,'Skritter words'!$A$1:$A$4411,1,0) -> 占
A68: 厶 | B68: =VLOOKUP(A68,'Skritter words'!$A$1:$A$4411,1,0) -> 厶
A69: 友 | B69: =VLOOKUP(A69,'Skritter words'!$A$1:$A$4411,1,0) -> 友
... A123: 走到 | B123: =VLOOKUP(A123,'Skritter words'!$A$1:$A$4411,1,0) -> 走到
A124: 走吧 | B124: =VLOOKUP(A124,'Skritter words'!$A$1:$A$4411,1,0) -> #N/A | C124: x
A125: 走开 | B125: =VLOOKUP(A125,'Skritter words'!$A$1:$A$4411,1,0) -> 走开
A126: 这个 | B126: =VLOOKUP(A126,'Skritter words'!$A$1:$A$4411,1,0) -> 这个
A127: 这种 | B127: =VLOOKUP(A127,'Skritter words'!$A$1:$A$4411,1,0) -> 这种
A128: 读 | B128: =VLOOKUP(A128,'Skritter words'!$A$1:$A$4411,1,0) -> 读
A129: 起 | B129: =VLOOKUP(A129,'Skritter words'!$A$1:$A$4411,1,0) -> 起
A130: 谁 | B130: =VLOOKUP(A130,'Skritter words'!$A$1:$A$4411,1,0) -> 谁
A131: 身后 | B131: =VLOOKUP(A131,'Skritter words'!$A$1:$A$4411,1,0) -> 身后
A132: 车 | B132: =VLOOKUP(A132,'Skritter words'!$A$1:$A$4411,1,0) -> 车
A133: 谢谢 | B133: =VLOOKUP(A133,'Skritter words'!$A$1:$A$4411,1,0) -> 谢谢
A134: 辶 | B134: =VLOOKUP(A134,'Skritter words'!$A$1:$A$4411,1,0) -> 辶
A135: 运 | B135: =VLOOKUP(A135,'Skritter words'!$A$1:$A$4411,1,0) -> 运
A136: 这些 | B136: =VLOOKUP(A136,'Skritter words'!$A$1:$A$4411,1,0) -> 这些
... A252: 来到 | B252: =VLOOKUP(A252,'Skritter words'!$A$1:$A$4411,1,0) -> 来到
A253: 6 点 | B253: =VLOOKUP(A253,'Skritter words'!$A$1:$A$4411,1,0) -> #N/A | C253: x
A254: 很多 | B254: =VLOOKUP(A254,'Skritter words'!$A$1:$A$4411,1,0) -> 很多
A255: 一个 | B255: =VLOOKUP(A255,'Skritter words'!$A$1:$A$4411,1,0) -> 一个
A256: 一 | B256: =VLOOKUP(A256,'Skritter words'!$A$1:$A$4411,1,0) -> 一
A257: 一家 | B257: =VLOOKUP(A257,'Skritter words'!$A$1:$A$4411,1,0) -> 一家
A258: 一天 | B258: =VLOOKUP(A258,'Skritter words'!$A$1:$A$4411,1,0) -> 一天
A259: 你好 | B259: =VLOOKUP(A259,'Skritter words'!$A$1:$A$4411,1,0) -> 你好
A260: 一会儿 | B260: =VLOOKUP(A260,'Skritter words'!$A$1:$A$4411,1,0) -> 一会儿
A261: 离开 | B261: =VLOOKUP(A261,'Skritter words'!$A$1:$A$4411,1,0) -> 离开
A262: 当 | B262: =VLOOKUP(A262,'Skritter words'!$A$1:$A$4411,1,0) -> 当
A263: 妈妈 | B263: =VLOOKUP(A263,'Skritter words'!$A$1:$A$4411,1,0) -> 妈妈
A264: 嘿 | B264: =VLOOKUP(A264,'Skritter words'!$A$1:$A$4411,1,0) -> 嘿
A265: 他来 | B265: =VLOOKUP(A265,'Skritter words'!$A$1:$A$4411,1,0) -> #N/A | C265: x
A266: 为了 | B266: =VLOOKUP(A266,'Skritter words'!$A$1:$A$4411,1,0) -> 为了
A267: 上 | B267: =VLOOKUP(A267,'Skritter words'!$A$1:$A$4411,1,0) -> 上
A268: 太 | B268: =VLOOKUP(A268,'Skritter words'!$A$1:$A$4411,1,0) -> 太
A269: 过来 | B269: =VLOOKUP(A269,'Skritter words'!$A$1:$A$4411,1,0) -> 过来
A270: 与 | B270: =VLOOKUP(A270,'Skritter words'!$A$1:$A$4411,1,0) -> 与
A271: 生活 | B271: =VLOOKUP(A271,'Skritter words'!$A$1:$A$4411,1,0) -> 生活
A272: 之 | B272: =VLOOKUP(A272,'Skritter words'!$A$1:$A$4411,1,0) -> 之
A273: 三月 | B273: =VLOOKUP(A273,'Skritter words'!$A$1:$A$4411,1,0) -> #N/A | C273: x
A274: 三 | B274: =VLOOKUP(A274,'Skritter words'!$A$1:$A$4411,1,0) -> 三
A275: 上午 | B275: =VLOOKUP(A275,'Skritter words'!$A$1:$A$4411,1,0) -> 上午
...

Sheet Skritter words
A1: 势
A2: 组织
A3: 不得不
A4: 纹
A5: 民众
A6: 降世神通
A7: 桃子
A8: 部长
A9: 弊
A10: 排队
A11: 眠
A12: 军团
... A4411: 石
