Workbook

Sheet Sheet1
A1: term | B1: status
A2: 上升 | B2: 0
A3: 伊丽莎白 | B3: 0
A4: 虹 | B4: 0
A5: 岛礁 | B5: 0
A6: 马小骥 | B6: 0
A7: 坦尼 | B7: 0
A8: 度 | B8: 3
A9: 壮观 | B9: 2
A10: 奥尔森 | B10: 0
A11: 友好 | B11: 3
A12: 冬兵 | B12: 0
A13: 耳语 | B13: 0
... A19728: 不休 | B19728: 0

Sheet New 4+5
A1: term | B1: status
A2: 度 | B2: 3
A3: 友好 | B3: 3
A4: 人头 | B4: 3
A5: 就 | B5: 3
A6: 应该 | B6: 3
A7: 怎么样 | B7: 3
A8: 等等等等 | B8: 3
A9: 只是 | B9: 3
A10: 见过 | B10: 3
A11: 帮助 | B11: 3
A12: 这么 | B12: 3
A13: 说 | B13: 3
... A5804: 门外 | B5804: 3

Sheet Old 4+5
A1: Word | B1: Len | C1: In new list?
A2: 势 | B2: =LEN(A2) -> 1 | C2: =VLOOKUP(A2,'New 4+5'!$A$2:$A$5804,1,0) -> 势
A3: 纹 | B3: =LEN(A3) -> 1 | C3: =VLOOKUP(A3,'New 4+5'!$A$2:$A$5804,1,0) -> 纹
A4: 弊 | B4: =LEN(A4) -> 1 | C4: =VLOOKUP(A4,'New 4+5'!$A$2:$A$5804,1,0) -> 弊
A5: 眠 | B5: =LEN(A5) -> 1 | C5: =VLOOKUP(A5,'New 4+5'!$A$2:$A$5804,1,0) -> 眠
A6: 毒 | B6: =LEN(A6) -> 1 | C6: =VLOOKUP(A6,'New 4+5'!$A$2:$A$5804,1,0) -> 毒
A7: 钩 | B7: =LEN(A7) -> 1 | C7: =VLOOKUP(A7,'New 4+5'!$A$2:$A$5804,1,0) -> 钩
A8: 顾 | B8: =LEN(A8) -> 1 | C8: =VLOOKUP(A8,'New 4+5'!$A$2:$A$5804,1,0) -> 顾
A9: 省 | B9: =LEN(A9) -> 1 | C9: =VLOOKUP(A9,'New 4+5'!$A$2:$A$5804,1,0) -> 省
A10: 劝 | B10: =LEN(A10) -> 1 | C10: =VLOOKUP(A10,'New 4+5'!$A$2:$A$5804,1,0) -> 劝
A11: 免 | B11: =LEN(A11) -> 1 | C11: =VLOOKUP(A11,'New 4+5'!$A$2:$A$5804,1,0) -> 免
A12: 艾 | B12: =LEN(A12) -> 1 | C12: =VLOOKUP(A12,'New 4+5'!$A$2:$A$5804,1,0) -> 艾
A13: 荣 | B13: =LEN(A13) -> 1 | C13: =VLOOKUP(A13,'New 4+5'!$A$2:$A$5804,1,0) -> 荣
... A5491: 司 美格 鲁肽 | B5491: =LEN(A5491) -> 7 | C5491: =VLOOKUP(A5491,'New 4+5'!$A$2:$A$5804,1,0) -> 司 美格 鲁肽
